[
    {
        "id": 1388534400000,
        "author": "Pete Hunt",
        "text": "Hey there!"
    },
    {
        "id": 1420070400000,
        "author": "Paul O’Shannessy",
        "text": "React is *great*!"
    },
    {
        "id": 1457231848956,
        "author": "me",
        "text": "hi"
    },
    {
        "id": 1111111111111,
        "author": "yer da",
        "text": "you are **grounded**"
    },
    {
        "id": 1457386157407,
        "author": "yer mom",
        "text": "off to **bed**"
    },
    {
        "id": 1457386319694,
        "author": "peter",
        "text": "##### Pie for **__dinner__**"
    },
    {
        "id": 1457386344861,
        "author": "john",
        "text": "no, **_pizza_** for dinner"
    }
]